{
  "kind": "singleType",
  "collectionName": "landing_pages",
  "info": {
    "singularName": "landing-page",
    "pluralName": "landing-pages",
    "displayName": "Landing Page"
  },
  "options": {
    "draftAndPublish": true
  },
  "pluginOptions": {},
  "attributes": {
    "heroHeading": {
      "type": "string"
    },
    "heroSubheading": {
      "type": "string"
    },
    "heroCopyHeading": {
      "type": "string"
    },
    "heroCopy": {
      "type": "string"
    },
    "heroMedia": {
      "type": "media",
      "multiple": false,
      "allowedTypes": [
        "images"
      ]
    },
    "content": {
      "type": "dynamiczone",
      "components": [
        "composite.accordions",
        "composite.bento",
        "composite.logo-cloud",
        "composite.cta-section",
        "composite.contact-form",
        "composite.generic-content",
        "composite.projects",
        "composite.testimonials"
      ]
    }
  }
}
